tensornet/__init__.py
tensornet-0.0.0.dist-info/LICENSE
tensornet-0.0.0.dist-info/METADATA
tensornet-0.0.0.dist-info/WHEEL
tensornet-0.0.0.dist-info/top_level.txt
tensornet-0.0.0.dist-info/RECORD
