Metadata-Version: 2.1
Name: tensornet
Version: 0.0.0
Summary: UNKNOWN
Home-page: UNKNOWN
Author: Arvin Singh Kushwaha
Author-email: arvin.singhk@gmail.com
License: UNKNOWN
Platform: UNKNOWN
Requires-Dist: numpy
